<!DOCTYPE ui:UiBinder SYSTEM "http://dl.google.com/gwt/DTD/xhtml.ent">
<ui:UiBinder xmlns:ui="urn:ui:com.google.gwt.uibinder"
	xmlns:g="urn:import:com.google.gwt.user.client.ui">
	<ui:style>
		.eastPanel {
			background-color: grey;
		}
		
		.westPanel {
			background-color: grey;
		}
		
		.northPanel {
			background-color: grey;
		}
		
		.southPanel {
			background-color: grey;
		}
		
		.centerPanel {
			background-color: grey;
		}
	</ui:style>
	<g:DockLayoutPanel unit='EM'>
		<g:north size='17.8'>
			<g:FlowPanel styleName="{style.northPanel}"/>
		</g:north>
		<g:west size='24.4'>
			<g:FlowPanel styleName="{style.westPanel}">
			</g:FlowPanel>
		</g:west>
		<g:center>
			<g:FlowPanel styleName="{style.centerPanel}">
				<g:TextBox text="Username" name="user" ui:field="user" width="150px" />
				<g:TextBox text="Password" name="pass" ui:field="pass" width="150px" />
				<g:Button width="160px" ui:field="button">Login</g:Button>
			</g:FlowPanel>
		</g:center>
		<g:east size='4.0'>
			<g:FlowPanel styleName="{style.eastPanel}" />
		</g:east>
		<g:south size="7.8">
			<g:FlowPanel styleName="{style.southPanel}">
			</g:FlowPanel>
		</g:south>
	</g:DockLayoutPanel>
</ui:UiBinder> 